pyvaloapi/__init__.py
pyvaloapi/client.py
pyvaloapi/local_api.py
pyvaloapi/request_class.py
pyvaloapi-1.2.dist-info/METADATA
pyvaloapi-1.2.dist-info/WHEEL
pyvaloapi-1.2.dist-info/top_level.txt
pyvaloapi-1.2.dist-info/RECORD
