Metadata-Version: 2.1
Name: pyvaloapi
Version: 1.2
Author: Mohamed Yassine Ahmed Ali
Author-email: <yassineahmedali02@gmail.com>
Keywords: python,api,valorant,games,gaming,http
Classifier: Development Status :: 1 - Planning
Classifier: Intended Audience :: Developers
Classifier: Programming Language :: Python :: 3
Classifier: Operating System :: Unix
Classifier: Operating System :: MacOS :: MacOS X
Classifier: Operating System :: Microsoft :: Windows
Requires-Dist: requests
